{
	"playlist": [
		{
			"spotifyID": "1mCUYpR3ZtwaqvcdCjgLuT",
			"youtubeID": "M5r0BZmeawA",
			"year": "2010",
			"animation": "Aziz",
			"keyframes": [
				{
					"timecode": "01:35:02"
				},
				{
					"timecode": "01:49:20",
					"actions": ["showThese"]
				},
				{
					"timecode": "1:49:28",
					"actions":	["showBeats"]
				},
				{
					"timecode": "01:50:07",
					"actions":	["showAre"]
				},
				{
					"timecode": "01:50:15",
					"actions":	["showDope"]
				},
				{
					"timecode": "01:51:10",
					"actions":	["showSubheading", "scrollIntro1"]
				},
				{
					"timecode": "01:51:11",
					"actions":	["showButton", "scrollIntro2"]
				},
				{
					"timecode": "01:53:00"
				}
			]
		},
		{
			"spotifyID": "06TqBu4Vi2DEu2F2wNTEnb",
			"youtubeID": "CDyrWWPt534",
			"year": "2004",
			"animation": "Kanye",
			"keyframes": [
				{
					"timecode": "00:10:10",
					"actions":	["breathing"]
				},
				{
					"timecode": "00:18:00",
					"bpm": "81.7",
					"actions": ["bop"]
				},
				{
					"timecode": "02:48:20",
					"actions":	["breathing"]
				}
			]
		},
		{
			"spotifyID": "2FgkwIXC52sHCbqVL8jE41",
			"youtubeID": "JCYAjGnvc7U",
			"year": "2005",
			"animation": "Kanye",
			"keyframes": [
				{
					"timecode": "00:06:05",
					"actions":	["breathing"]
				},
				{
					"timecode": "02:49:00",
					"actions":	["breathing"]
				}
			]
		},
		{
			"spotifyID": "7rWwv1ePazmRzmJs4sARhI",
			"youtubeID": "hCx4LfPDWSY",
			"year": "2007",
			"animation": "Kanye",
			"keyframes": [
				{
					"timecode": "00:10:00",
					"actions":	["breathing"]
				},
				{
					"timecode": "05:05:25",
					"actions":	["breathing"]
				}
			]
		}
	]
}
